gym_zelda_1/__init__.py
gym_zelda_1/actions.py
gym_zelda_1/zelda_env.py
gym_zelda_1/_app/__init__.py
gym_zelda_1/_app/cli.py
gym_zelda_1/_roms/Zelda_1.nes
gym_zelda_1-0.2.2.dist-info/LICENSE
gym_zelda_1-0.2.2.dist-info/METADATA
gym_zelda_1-0.2.2.dist-info/WHEEL
gym_zelda_1-0.2.2.dist-info/entry_points.txt
gym_zelda_1-0.2.2.dist-info/top_level.txt
gym_zelda_1-0.2.2.dist-info/RECORD
