Metadata-Version: 2.1
Name: gym_zelda_1
Version: 0.2.2
Summary: Super Mario Bros. for OpenAI Gym
Home-page: https://github.com/Kautenja/gym-super-mario-bros
Author: Christian Kauten
Author-email: kautencreations@gmail.com
License: Proprietary
Keywords: OpenAI-Gym NES The-Legend-Of-Zelda Zelda-1 Reinforcement-Learning-Environment
Platform: UNKNOWN
Classifier: License :: Free For Educational Use
Classifier: Development Status :: 1 - Planning
Classifier: Intended Audience :: Developers
Classifier: Intended Audience :: Science/Research
Classifier: Operating System :: MacOS :: MacOS X
Classifier: Operating System :: POSIX :: Linux
Classifier: Operating System :: Microsoft :: Windows
Classifier: Programming Language :: Python :: 2.7
Classifier: Programming Language :: Python :: 3.5
Classifier: Programming Language :: Python :: 3.6
Classifier: Topic :: Games/Entertainment :: Side-Scrolling/Arcade Games
Classifier: Topic :: Scientific/Engineering :: Artificial Intelligence
